django_jquery_datatables/__init__.py
django_jquery_datatables/utils.py
django_jquery_datatables-1.1.0.dist-info/License.txt
django_jquery_datatables-1.1.0.dist-info/METADATA
django_jquery_datatables-1.1.0.dist-info/WHEEL
django_jquery_datatables-1.1.0.dist-info/top_level.txt
django_jquery_datatables-1.1.0.dist-info/RECORD
