Metadata-Version: 2.1
Name: django_jquery_datatables
Version: 1.1.0
Summary: Python library that integrates the popular jQuery DataTables library with Django projects.
Home-page: https://github.com/Saliksheraz/django_jquery_datatables.git
Author: Salik Sheraz
Author-email: salik.sheraz@it-masons.com
License-File: License.txt
Requires-Dist: Django >=3.0.0
Requires-Dist: requests >=2.0.0
Requires-Dist: django-rest-framework >=0.1.0
Requires-Dist: urllib3
